XiocaAPI/__init__.py
xiocaapi-0.2.2.dist-info/METADATA
xiocaapi-0.2.2.dist-info/WHEEL
xiocaapi-0.2.2.dist-info/RECORD
