Metadata-Version: 2.4
Name: XiocaAPI
Version: 0.2.2
Summary: Асинхронный и синхронный клиент для Xioca API
Project-URL: Homepage, https://github.com/shashachkaaa/xiocaapi
Project-URL: Bug Tracker, https://github.com/shashachkaaa/xiocaapi/issues
Author-email: shashachkaaa <sasaxtwink@gmail.com>
Classifier: Intended Audience :: Developers
Classifier: License :: OSI Approved :: MIT License
Classifier: Operating System :: OS Independent
Classifier: Programming Language :: Python :: 3
Classifier: Topic :: Software Development :: Libraries :: Python Modules
Requires-Python: >=3.8
Requires-Dist: aiohttp>=3.8.0
Requires-Dist: pydantic>=2.0.0
Requires-Dist: requests>=2.20.0
